code/__init__.py
code/pchslibrary.py
pchslibrary-0.0.1.dist-info/LICENSE
pchslibrary-0.0.1.dist-info/METADATA
pchslibrary-0.0.1.dist-info/WHEEL
pchslibrary-0.0.1.dist-info/top_level.txt
pchslibrary-0.0.1.dist-info/RECORD
