Metadata-Version: 2.1
Name: pchslibrary
Version: 0.0.1
Summary: My library is about defs of my collection
Author: PCH_125
Author-email: phanchanhung12055@gmail.com
Requires-Python: >=3.7
License-File: LICENSE
Requires-Dist: numpy
Requires-Dist: roman
